MANIFEST.in
README.rst
setup.py
flask_segmentio/__init__.py
flask_segmentio.egg-info/PKG-INFO
flask_segmentio.egg-info/SOURCES.txt
flask_segmentio.egg-info/dependency_links.txt
flask_segmentio.egg-info/not-zip-safe
flask_segmentio.egg-info/requires.txt
flask_segmentio.egg-info/top_level.txt