Metadata-Version: 1.1
Name: flask-segmentio
Version: 0.1.0
Summary: Adds SegmentIO support to your Flask application
Home-page: http://github.com/iromli/flask-segmentio
Author: Isman Firmansyah
Author-email: isman.firmansyah@gmail.com
License: MIT
Platform: UNKNOWN
Classifier: Environment :: Web Environment
Classifier: Intended Audience :: Developers
Classifier: License :: OSI Approved :: MIT License
Classifier: Topic :: Internet :: WWW/HTTP :: Dynamic Content
Classifier: Topic :: Software Development :: Libraries :: Python Modules
Classifier: Programming Language :: Python
Classifier: Programming Language :: Python :: 2
Classifier: Programming Language :: Python :: 2.7
Classifier: Programming Language :: Python :: 3
Classifier: Programming Language :: Python :: 3.4
